LICENSE
MANIFEST.in
README.rst
setup.py
rapyd_db/__init__.py
rapyd_db/loggingadapter.py
rapyd_db/utils.py
rapyd_db.egg-info/PKG-INFO
rapyd_db.egg-info/SOURCES.txt
rapyd_db.egg-info/dependency_links.txt
rapyd_db.egg-info/requires.txt
rapyd_db.egg-info/top_level.txt
rapyd_db/backends/__init__.py
rapyd_db/backends/mongo.py
rapyd_db/backends/mssql.py
rapyd_db/backends/mysql.py
rapyd_db/tests/__init__.py
rapyd_db/tests/test_mongo.py
rapyd_db/tests/test_mssql.py
rapyd_db/tests/test_mysql.py