Metadata-Version: 2.1
Name: rapyd-db
Version: 0.0.8
Summary: An opinionated lightweight wrapper around various DB backend drivers.
Home-page: https://github.com/karthicraghupathi/rapyd_db
Author: Karthic Raghupathi
Author-email: karthicr@gmail.com
License:                                  Apache License
